[{"clue":"Ale holders","answer":"TUNS","a":"03","b":"9"},{"clue":"Feature of some glasses","answer":"TINT","a":"03","b":"9"},{"clue":"\"___, We Love Thee\" (song)","answer":"UTAH","a":"03","b":"9"},{"clue":"Off base, perhaps","answer":"ONLEAVE","a":"03","b":"9"},{"clue":"\"Indeed\"","answer":"QUITESO","a":"03","b":"9"},{"clue":"He played Van Doren in \"Quiz Show\"","answer":"FIENNES","a":"03","b":"9"},{"clue":"Like some sources","answer":"UNNAMED","a":"03","b":"9"},{"clue":"Encourages","answer":"FOSTERS","a":"03","b":"9"},{"clue":"Gallery patron, maybe","answer":"ESTHETE","a":"03","b":"9"},{"clue":"Sounds from a cornfield","answer":"CAWS","a":"03","b":"3"},{"clue":"Winter melon","answer":"CASABA","a":"03","b":"3"},{"clue":"Evil-repelling charm","answer":"AMULET","a":"03","b":"3"},{"clue":"Sang like a canary","answer":"WARBLED","a":"03","b":"3"},{"clue":"Hoops turnover","answer":"STEAL","a":"03","b":"3"},{"clue":"Sonny who sang \"Laugh at Me\"","answer":"BONO","a":"03","b":"3"},{"clue":"Cutie pie","answer":"BABYDOLL","a":"03","b":"3"},{"clue":"Eggs, to biologists","answer":"OVA","a":"03","b":"3"},{"clue":"Strikeout king Ryan","answer":"NOLAN","a":"03","b":"3"},{"clue":"Surfing the Net","answer":"ONLINE","a":"03","b":"3"},{"clue":"\"Fiddlesticks!\"","answer":"PSHAW","a":"03","b":"3"},{"clue":"___-mutuel","answer":"PARI","a":"03","b":"3"},{"clue":"Slop eaters","answer":"SWINE","a":"03","b":"3"},{"clue":"Waits awhile","answer":"HANGSON","a":"03","b":"3"},{"clue":"Alias","answer":"AKA","a":"03","b":"3"},{"clue":"Director Craven","answer":"WES","a":"03","b":"3"},{"clue":"Part of a Latin 101 trio","answer":"AMAT","a":"03","b":"3"},{"clue":"\"___ calling\"","answer":"AVON","a":"03","b":"3"},{"clue":"Not in dreamland","answer":"AWAKE","a":"03","b":"3"},{"clue":"\"You bet!\"","answer":"SURE","a":"03","b":"3"},{"clue":"They're often on their toes","answer":"BALLERINAS","a":"03","b":"3"},{"clue":"Big times","answer":"ERAS","a":"03","b":"3"},{"clue":"Capital on the Hudson","answer":"ALBANY","a":"03","b":"3"},{"clue":"Persistent, as a backache","answer":"NAGGING","a":"03","b":"3"},{"clue":"Being broadcast","answer":"AIRING","a":"03","b":"3"},{"clue":"Poisonous plant","answer":"BELLADONNA","a":"03","b":"3"},{"clue":"Autobahn auto","answer":"OPEL","a":"03","b":"3"},{"clue":"Hockey great Phil, familiarly","answer":"ESPO","a":"03","b":"3"},{"clue":"Unimpressive brain size","answer":"PEA","a":"03","b":"3"},{"clue":"Suffix with deposit or reposit","answer":"ORY","a":"03","b":"3"},{"clue":"Broke a fast","answer":"ATE","a":"03","b":"3"},{"clue":"46-Across belonged to it","answer":"GOP","a":"03","b":"3"},{"clue":"Mentalist's claim","answer":"ESP","a":"03","b":"3"},{"clue":"Miner's tool","answer":"PICKAXE","a":"03","b":"3"},{"clue":"Not 'neath","answer":"OER","a":"03","b":"3"},{"clue":"Golf course bend","answer":"DOGLEG","a":"03","b":"3"},{"clue":"Geisha's sash","answer":"OBI","a":"03","b":"3"},{"clue":"Nautilus locale","answer":"GYM","a":"03","b":"3"},{"clue":"\"Forget it!\"","answer":"IXNAY","a":"03","b":"3"},{"clue":"Classic Jaguar","answer":"XKE","a":"03","b":"3"},{"clue":"1971 Tom Laughlin cult film","answer":"BILLYJACK","a":"03","b":"3"},{"clue":"Monopoly corner square","answer":"JAIL","a":"03","b":"3"},{"clue":"Come to","answer":"ARRIVEAT","a":"03","b":"3"},{"clue":"Conductor Mehta","answer":"ZUBIN","a":"03","b":"3"},{"clue":"Nada","answer":"ZIP","a":"03","b":"3"},{"clue":"Hawaiian strings","answer":"UKE","a":"03","b":"3"},{"clue":"Fancy British wheels","answer":"BENTLEY","a":"03","b":"3"},{"clue":"Piece of bingo equipment","answer":"MARKER","a":"03","b":"3"},{"clue":"\"Batman\" villain","answer":"RIDDLER","a":"03","b":"3"},{"clue":"50's nickname","answer":"IKE","a":"03","b":"3"},{"clue":"Not swallow easily","answer":"GAG","a":"03","b":"3"},{"clue":"Aid in crime","answer":"ABET","a":"03","b":"3"},{"clue":"\"Batman\" setting","answer":"GOTHAM","a":"03","b":"3"},{"clue":"Nest egg, of a sort: Abbr.","answer":"IRA","a":"03","b":"3"},{"clue":"Uncertainties","answer":"IFS","a":"03","b":"3"},{"clue":"Gassed up","answer":"FUELED","a":"03","b":"3"},{"clue":"Big name in swimwear","answer":"SPEEDO","a":"03","b":"3"},{"clue":"Puts in writing","answer":"PENS","a":"03","b":"3"},{"clue":"Dieter's fare","answer":"SALAD","a":"03","b":"3"},{"clue":"Bungled","answer":"BOLLIXEDUP","a":"03","b":"3"},{"clue":"Nutty as a fruitcake","answer":"LOOPY","a":"03","b":"3"},{"clue":"A","answer":"ENERO","a":"03","b":"3"},{"clue":"Become fond of","answer":"TAKETO","a":"03","b":"3"},{"clue":"\"Show Boat\" composer","answer":"KERN","a":"03","b":"3"},{"clue":"Buyer","answer":"VENDEE","a":"03","b":"3"},{"clue":"Bit of forensic evidence","answer":"BULLETHOLE","a":"03","b":"3"},{"clue":"Cry from Scrooge","answer":"BAH","a":"03","b":"3"},{"clue":"Italian article","answer":"UNA","a":"03","b":"3"},{"clue":"Fleur-de-___","answer":"LIS","a":"03","b":"3"},{"clue":"Glamour rival","answer":"ELLE","a":"03","b":"3"},{"clue":"Proximate, to poets","answer":"ANEAR","a":"03","b":"3"},{"clue":"Capital of Samoa","answer":"APIA","a":"03","b":"3"},{"clue":"Marsh growth","answer":"REED","a":"03","b":"3"},{"clue":"\"The Creation\" composer","answer":"HAYDN","a":"03","b":"3"},{"clue":"Classic computer game","answer":"MYST","a":"03","b":"3"},{"clue":"Novus ___ seclorum (phrase on a dollar)","answer":"ORDO","a":"03","b":"3"},{"clue":"Like a Dagwood sandwich","answer":"PILEDHIGH","a":"03","b":"11"},{"clue":"Make an unannounced call","answer":"POPIN","a":"03","b":"11"},{"clue":"Floored","answer":"INAWE","a":"03","b":"11"},{"clue":"\"The Wizard of Oz\" producer","answer":"LEROY","a":"03","b":"11"},{"clue":"\"Voice of Israel\" author","answer":"EBAN","a":"03","b":"11"},{"clue":"Fluvial plains","answer":"DELTAS","a":"03","b":"11"},{"clue":"\"Good\" cholesterol, briefly","answer":"HDL","a":"03","b":"11"},{"clue":"Unpleasant thing to invoke","answer":"IRE","a":"03","b":"11"},{"clue":"Provision in some executives' contracts","answer":"GOLDENPARACHUTE","a":"03","b":"11"},{"clue":"Some field workers","answer":"HOERS","a":"03","b":"11"},{"clue":"Scam targets","answer":"SAPS","a":"03","b":"11"},{"clue":"E.P.A. concern","answer":"SEWAGE","a":"03","b":"11"},{"clue":"Stopping system","answer":"AIRBRAKES","a":"03","b":"11"},{"clue":"Stickers","answer":"PRICETAGS","a":"03","b":"11"},{"clue":"Stagecraft?","answer":"SETDESIGN","a":"03","b":"11"},{"clue":"Kind of flat","answer":"ONEBEDROOM","a":"03","b":"11"},{"clue":"Experts on physiol.","answer":"MDS","a":"03","b":"11"},{"clue":"Hibernia","answer":"EIRE","a":"03","b":"11"},{"clue":"Corresponded to","answer":"PARALLELED","a":"03","b":"11"},{"clue":"Letter of the law?","answer":"WRIT","a":"03","b":"11"},{"clue":"\"Absolutely not!\"","answer":"IWONT","a":"03","b":"11"},{"clue":"Treating people: Abbr.","answer":"DRS","a":"03","b":"11"},{"clue":"Opening run","answer":"ABCD","a":"03","b":"11"},{"clue":"Napoleon's \"bravest of the brave\"","answer":"NEY","a":"03","b":"11"},{"clue":"Fine things in Bilbao","answer":"ARTES","a":"03","b":"11"},{"clue":"What's left, in Lyon","answer":"RESTE","a":"03","b":"11"},{"clue":"\"A Confederacy of Dunces\" author","answer":"TOOLE","a":"03","b":"11"},{"clue":"Feel the same","answer":"AGREE","a":"03","b":"11"},{"clue":"Not grounded, perhaps","answer":"ASEA","a":"03","b":"11"},{"clue":"Hit with, as a pickup line","answer":"USEON","a":"03","b":"11"},{"clue":"Link letters?","answer":"URL","a":"03","b":"11"},{"clue":"Stadium row","answer":"SEATS","a":"03","b":"11"},{"clue":"Cutting evidence","answer":"SCAR","a":"03","b":"11"},{"clue":"Like some watches","answer":"SWISSMADE","a":"03","b":"11"},{"clue":"One spotted in an alley","answer":"CALICOCAT","a":"03","b":"11"},{"clue":"Edward VII's queen","answer":"ALEXANDRA","a":"03","b":"11"},{"clue":"1982 title role for Meryl Streep","answer":"SOPHIE","a":"03","b":"11"},{"clue":"Radisson rival","answer":"HYATT","a":"03","b":"11"},{"clue":"Carpet fiber","answer":"ISTLE","a":"03","b":"11"},{"clue":"Alaskan Klee ___ (small dog breed)","answer":"KAI","a":"03","b":"11"},{"clue":"1929 Variety headline","answer":"WALLSTLAYSANEGG","a":"03","b":"11"},{"clue":"Roy Rogers's original surname","answer":"SLYE","a":"03","b":"11"},{"clue":"Rural refusal","answer":"NAW","a":"03","b":"11"},{"clue":"Qu","answer":"ILE","a":"03","b":"11"},{"clue":"Eye salaciously","answer":"LEERAT","a":"03","b":"11"},{"clue":"Club: Abbr.","answer":"ASSN","a":"03","b":"11"},{"clue":"A mile a minute","answer":"SIXTY","a":"03","b":"11"},{"clue":"Remnants","answer":"TRACES","a":"03","b":"11"},{"clue":"Counselor-___","answer":"ATLAW","a":"03","b":"11"},{"clue":"If all goes right","answer":"ATBEST","a":"03","b":"11"},{"clue":"Close call","answer":"SCARE","a":"03","b":"11"},{"clue":"Square dance group, e.g.","answer":"OCTET","a":"03","b":"11"},{"clue":"Yellow shade","answer":"OCHER","a":"03","b":"11"},{"clue":"Some linemen: Abbr.","answer":"RTS","a":"03","b":"11"},{"clue":"Medieval stringed instrument","answer":"REBEC","a":"03","b":"11"},{"clue":"It has a bed","answer":"TRUCK","a":"03","b":"11"},{"clue":"Some noncoms: Abbr.","answer":"SSGTS","a":"03","b":"11"},{"clue":"Marisa's \"My Cousin Vinny\" role","answer":"MONA","a":"03","b":"11"},{"clue":"Prussian pronoun","answer":"ICH","a":"03","b":"11"},{"clue":"Acre's land: Abbr.","answer":"ISR","a":"03","b":"11"},{"clue":"Ring brothers of the 1930's","answer":"BAERS","a":"03","b":"11"},{"clue":"It's plucked in Parma","answer":"ARPA","a":"03","b":"11"},{"clue":"Adapter designation","answer":"ACDC","a":"03","b":"11"},{"clue":"Enthusiastic snapper","answer":"SHUTTERBUG","a":"03","b":"11"},{"clue":"Refrain syllable","answer":"TRA","a":"03","b":"11"},{"clue":"Crib sheet user","answer":"TOT","a":"03","b":"11"},{"clue":"It may make you do something foolish","answer":"DARE","a":"03","b":"11"},{"clue":"Survey of the past","answer":"RETROSPECT","a":"03","b":"11"},{"clue":"Flight data, briefly","answer":"ETAS","a":"03","b":"11"},{"clue":"Charges anew","answer":"REATTACKS","a":"03","b":"11"},{"clue":"An article may be written on it","answer":"SPEC","a":"03","b":"5"},{"clue":"Bay Area patrollers: Abbr.","answer":"SFPD","a":"03","b":"5"},{"clue":"Carson predecessor","answer":"PAAR","a":"03","b":"5"},{"clue":"Miscalculates","answer":"ERRS","a":"03","b":"5"},{"clue":"Soda fountain choices","answer":"COKES","a":"03","b":"5"},{"clue":"Purse part, often","answer":"STRAP","a":"03","b":"5"},{"clue":"Hid","answer":"STASHED","a":"03","b":"5"},{"clue":"Catches some rays","answer":"TANS","a":"03","b":"5"},{"clue":"Toupee, slangily","answer":"RUG","a":"03","b":"5"},{"clue":"Copy","answer":"APE","a":"03","b":"5"},{"clue":"Keep going","answer":"PERSIST","a":"03","b":"5"},{"clue":"Cake with a kick","answer":"BABA","a":"03","b":"5"},{"clue":"1930's heavyweight champ Max","answer":"BAER","a":"03","b":"5"},{"clue":"Acid-neutralizing compound","answer":"ALKALI","a":"03","b":"5"},{"clue":"Complained","answer":"BEEFED","a":"03","b":"5"},{"clue":"Selling points","answer":"ASSETS","a":"03","b":"5"},{"clue":"Baccarat alternative","answer":"FARO","a":"03","b":"5"},{"clue":"Brownish gray","answer":"TAUPE","a":"03","b":"5"},{"clue":"Bass products","answer":"ALES","a":"03","b":"5"},{"clue":"Yellowstone figure","answer":"PARKRANGER","a":"03","b":"5"},{"clue":"German industrial valley","answer":"RUHR","a":"03","b":"5"},{"clue":"___ out (barely gets)","answer":"EKES","a":"03","b":"5"},{"clue":"\"Yertle the Turtle\" author","answer":"DRSEUSS","a":"03","b":"5"},{"clue":"Rake with fire","answer":"STRAFE","a":"03","b":"5"},{"clue":"\"Don't ___ on me\"","answer":"TREAD","a":"03","b":"5"},{"clue":"\"Quiet!\"","answer":"SHH","a":"03","b":"5"},{"clue":"Where cubs are raised","answer":"LAIR","a":"03","b":"5"},{"clue":"Daewoo model","answer":"LEGANZA","a":"03","b":"5"},{"clue":"Operatic passage","answer":"ARIOSO","a":"03","b":"5"},{"clue":"Permit","answer":"LET","a":"03","b":"5"},{"clue":"\"I know the answer!\"","answer":"AHA","a":"03","b":"5"},{"clue":"Toward the rear","answer":"AFT","a":"03","b":"5"},{"clue":"Tint","answer":"HUE","a":"03","b":"5"},{"clue":"Egyptian viper","answer":"ASP","a":"03","b":"5"},{"clue":"Contract bridge tactics","answer":"REVERSEBIDS","a":"03","b":"5"},{"clue":"Blood pressure, body temperature, etc.","answer":"VITALS","a":"03","b":"5"},{"clue":"Campy 1958 sci-fi film, with \"The\"","answer":"BLOB","a":"03","b":"5"},{"clue":"Bother","answer":"FUSS","a":"03","b":"5"},{"clue":"Split-off group","answer":"SECT","a":"03","b":"5"},{"clue":"Like modern clocks and recordings","answer":"DIGITAL","a":"03","b":"5"},{"clue":"Home on the range","answer":"TEPEE","a":"03","b":"5"},{"clue":"Jetsons' lad","answer":"ELROY","a":"03","b":"5"},{"clue":"Divine path, in Asian religions","answer":"TAO","a":"03","b":"5"},{"clue":"Firm belief","answer":"DOGMA","a":"03","b":"5"},{"clue":"Came down with","answer":"GOT","a":"03","b":"5"},{"clue":"Unaccounted-for G.I.","answer":"MIA","a":"03","b":"5"},{"clue":"Saint-Moritz sight","answer":"ALP","a":"03","b":"5"},{"clue":"Wash","answer":"CLEANSE","a":"03","b":"5"},{"clue":"Entered gradually","answer":"EASEDIN","a":"03","b":"5"},{"clue":"Main courses","answer":"ENTREES","a":"03","b":"5"},{"clue":"Heat to more than 212","answer":"BOIL","a":"03","b":"5"},{"clue":"Where weapons are forbidden","answer":"NEUTRALZONE","a":"03","b":"5"},{"clue":"Zero","answer":"NOTONE","a":"03","b":"5"},{"clue":"Reworked, as text","answer":"EDITED","a":"03","b":"5"},{"clue":"Log-on name","answer":"USERID","a":"03","b":"5"},{"clue":"Rocker Clapton","answer":"ERIC","a":"03","b":"5"},{"clue":"Need for a keg","answer":"TAP","a":"03","b":"5"},{"clue":"Takes too many tranqs, say","answer":"ODS","a":"03","b":"5"},{"clue":"Peak SE of Olympus","answer":"OSSA","a":"03","b":"5"},{"clue":"\"La-la\" lead-in","answer":"TRA","a":"03","b":"5"},{"clue":"Fall into ___ (get caught)","answer":"ATRAP","a":"03","b":"5"},{"clue":"Color, as a hippie's shirt","answer":"TIEDYE","a":"03","b":"5"},{"clue":"Carson ___ of MTV","answer":"DALY","a":"03","b":"5"},{"clue":"Breakaway country from Ethiopia","answer":"ERITREA","a":"03","b":"5"},{"clue":"Malevolence","answer":"EVIL","a":"03","b":"5"},{"clue":"Marathon","answer":"RACE","a":"03","b":"5"},{"clue":"Pound of literature","answer":"EZRA","a":"03","b":"5"},{"clue":"Yeoman's yeses","answer":"AYES","a":"03","b":"5"},{"clue":"Other, in Oaxaca","answer":"OTRA","a":"03","b":"5"},{"clue":"Send around the bend","answer":"DRIVECRAZY","a":"03","b":"5"},{"clue":"Genetic info carrier","answer":"RNA","a":"03","b":"5"},{"clue":"Uganda's Amin","answer":"IDI","a":"03","b":"5"},{"clue":"Astronaut Armstrong","answer":"NEIL","a":"03","b":"5"},{"clue":"Nonstudio film","answer":"INDIE","a":"03","b":"5"},{"clue":"Plowing unit","answer":"ACRE","a":"03","b":"5"},{"clue":"Swirl","answer":"EDDY","a":"03","b":"5"},{"clue":"Achieves perfectly","answer":"NAILS","a":"03","b":"5"},{"clue":"They're split for soup","answer":"PEAS","a":"03","b":"5"},{"clue":"Ocean motion","answer":"TIDE","a":"03","b":"12"},{"clue":"Morsel","answer":"TIDBIT","a":"03","b":"12"},{"clue":"Frigid time","answer":"ICEAGE","a":"03","b":"12"},{"clue":"Plum variety","answer":"DAMSON","a":"03","b":"12"},{"clue":"Slaughter of Cooperstown","answer":"ENOS","a":"03","b":"12"},{"clue":"Epistle apostle","answer":"PAUL","a":"03","b":"12"},{"clue":"Danish filler","answer":"PRUNE","a":"03","b":"12"},{"clue":"Crash cushioner","answer":"AIRBAG","a":"03","b":"12"},{"clue":"The Bruins of the N.C.A.A.","answer":"UCLA","a":"03","b":"12"},{"clue":"Not as much","answer":"LESS","a":"03","b":"12"},{"clue":"Get-go","answer":"ONSET","a":"03","b":"12"},{"clue":"Bean on the screen","answer":"ORSON","a":"03","b":"12"},{"clue":"Ill feelings","answer":"NOLOVELOST","a":"03","b":"12"},{"clue":"Screenwriter's creation","answer":"SCENARIO","a":"03","b":"12"},{"clue":"Barely make, with \"out\"","answer":"EKE","a":"03","b":"12"},{"clue":"\"For shame!\"","answer":"TSK","a":"03","b":"12"},{"clue":"Words of confidence","answer":"ICAN","a":"03","b":"12"},{"clue":"\"Dirty\" Cajun dish","answer":"RICE","a":"03","b":"12"},{"clue":"Makes some music, like the Stones","answer":"ROCKS","a":"03","b":"12"},{"clue":"Tape for a music exec","answer":"DEMO","a":"03","b":"12"},{"clue":"WWW addresses","answer":"URLS","a":"03","b":"12"},{"clue":"Aerodynamically designed","answer":"SLEEK","a":"03","b":"12"},{"clue":"Fish playing a woodwind?","answer":"BASSONBASSOON","a":"03","b":"12"},{"clue":"___ a time","answer":"ONEAT","a":"03","b":"12"},{"clue":"___ Nevadas","answer":"SIERRA","a":"03","b":"12"},{"clue":"\"May ___ now?\"","answer":"IGO","a":"03","b":"12"},{"clue":"PBS funder","answer":"NEA","a":"03","b":"12"},{"clue":"To no avail","answer":"INVAIN","a":"03","b":"12"},{"clue":"Get ___ a good thing","answer":"INON","a":"03","b":"12"},{"clue":"Prefix with profit","answer":"NON","a":"03","b":"12"},{"clue":"Not relaxed","answer":"TENSE","a":"03","b":"12"},{"clue":"Doodler's aid","answer":"SCRAPPAPER","a":"03","b":"12"},{"clue":"Auctioneer's cry","answer":"GONE","a":"03","b":"12"},{"clue":"Coveted statue","answer":"OSCAR","a":"03","b":"12"},{"clue":"Fed. hush-hush group","answer":"NSA","a":"03","b":"12"},{"clue":"Cube maker Rubik","answer":"ERNO","a":"03","b":"12"},{"clue":"Unmannered sort","answer":"CAD","a":"03","b":"12"},{"clue":"\"I'm all ears!\"","answer":"DOTELL","a":"03","b":"12"},{"clue":"Outdated atlas abbr.","answer":"SSR","a":"03","b":"12"},{"clue":"Pride member","answer":"LION","a":"03","b":"12"},{"clue":"Looney Tunes horse-drawn conveyance?","answer":"CARTONCARTOON","a":"03","b":"12"},{"clue":"Mafia bigwig","answer":"CAPO","a":"03","b":"12"},{"clue":"Mushroom cloud producer","answer":"ATOMBOMB","a":"03","b":"12"},{"clue":"Pro-gun rights org.","answer":"NRA","a":"03","b":"12"},{"clue":"Bring up the rear","answer":"TRAIL","a":"03","b":"12"},{"clue":"___ Hari (spy)","answer":"MATA","a":"03","b":"12"},{"clue":"Brit's raincoat","answer":"MAC","a":"03","b":"12"},{"clue":"La preceder","answer":"TRA","a":"03","b":"12"},{"clue":"___ gratia artis (MGM motto)","answer":"ARS","a":"03","b":"12"},{"clue":"Per unit","answer":"APOP","a":"03","b":"12"},{"clue":"Banjoist Scruggs","answer":"EARL","a":"03","b":"12"},{"clue":"Maze scurrier, maybe","answer":"LABRAT","a":"03","b":"12"},{"clue":"Chance for a hit","answer":"ATBAT","a":"03","b":"12"},{"clue":"Dance energetically","answer":"BOOGIE","a":"03","b":"12"},{"clue":"Famed Harlem theater","answer":"APOLLO","a":"03","b":"12"},{"clue":"Religious principles","answer":"TENETS","a":"03","b":"12"},{"clue":"Force","answer":"COMPEL","a":"03","b":"12"},{"clue":"Spanish princess","answer":"ELENA","a":"03","b":"12"},{"clue":"Will Smith biopic","answer":"ALI","a":"03","b":"12"},{"clue":"Soup scoop","answer":"LADLE","a":"03","b":"12"},{"clue":"Expose, in verse","answer":"OPE","a":"03","b":"12"},{"clue":"Dirigible party?","answer":"BALLONBALLOON","a":"03","b":"12"},{"clue":"Gymnast Korbut","answer":"OLGA","a":"03","b":"12"},{"clue":"\"High\" time","answer":"NOON","a":"03","b":"12"},{"clue":"Take it easy","answer":"LOLL","a":"03","b":"12"},{"clue":"Hillside","answer":"SLOPE","a":"03","b":"12"},{"clue":"Barrett of Pink Floyd","answer":"SYD","a":"03","b":"12"},{"clue":"General in gray","answer":"LEE","a":"03","b":"12"},{"clue":"Prayer addressee","answer":"LORD","a":"03","b":"12"},{"clue":"Look up and down","answer":"OGLE","a":"03","b":"12"},{"clue":"Red Sea land","answer":"YEMEN","a":"03","b":"12"},{"clue":"Score for Mia Hamm","answer":"GOAL","a":"03","b":"12"},{"clue":"Cheery tune","answer":"LILT","a":"03","b":"12"},{"clue":"Actress Winger","answer":"DEBRA","a":"03","b":"12"},{"clue":"Fork over, with \"up\"","answer":"ANTE","a":"03","b":"12"},{"clue":"Many August births","answer":"LEOS","a":"03","b":"12"},{"clue":"Subject of a court order","answer":"WIRETAP","a":"03","b":"10"},{"clue":"Cleaning vessel","answer":"WASHPOT","a":"03","b":"10"},{"clue":"Last song recorded by the Beatles","answer":"IMEMINE","a":"03","b":"10"},{"clue":"Not so likely","answer":"REMOTER","a":"03","b":"10"},{"clue":"Tosser of the Apple of Discord","answer":"ERIS","a":"03","b":"10"},{"clue":"Material for a whitesmith","answer":"TIN","a":"03","b":"10"},{"clue":"Yucca's plant family","answer":"AGAVE","a":"03","b":"10"},{"clue":"Pleasant","answer":"POLITE","a":"03","b":"10"},{"clue":"Credit","answer":"ASCRIBE","a":"03","b":"10"},{"clue":"Qintar spender","answer":"ALBANIAN","a":"03","b":"10"},{"clue":"Old letter opener","answer":"SIRS","a":"03","b":"10"},{"clue":"Early second-century date","answer":"CVI","a":"03","b":"10"},{"clue":"Oregon college","answer":"REED","a":"03","b":"10"},{"clue":"Classic work with 34 cantos","answer":"INFERNO","a":"03","b":"10"},{"clue":"Business, facetiously","answer":"BEESWAX","a":"03","b":"10"},{"clue":"Whirls","answer":"EDDIES","a":"03","b":"10"},{"clue":"Name after which the New World is named","answer":"AMERIGO","a":"03","b":"10"},{"clue":"Infused with energy","answer":"LIVENED","a":"03","b":"10"},{"clue":"Formative","answer":"SEMINAL","a":"03","b":"10"},{"clue":"Having some intelligence","answer":"BRIEFED","a":"03","b":"10"},{"clue":"Some modern bill payers, for short","answer":"HMOS","a":"03","b":"10"},{"clue":"Photo ID's","answer":"VISAS","a":"03","b":"10"},{"clue":"One concerned with bouquets","answer":"SOMMELIER","a":"03","b":"10"},{"clue":"50's sitcom name","answer":"DESI","a":"03","b":"10"},{"clue":"Set (against)","answer":"PIT","a":"03","b":"10"},{"clue":"Divulge","answer":"LETON","a":"03","b":"10"},{"clue":"Schlemiel","answer":"LOSER","a":"03","b":"10"},{"clue":"Literary monogram","answer":"RWE","a":"03","b":"10"},{"clue":"\"I'm not ___ complain ...\"","answer":"ONETO","a":"03","b":"10"},{"clue":"Bathwear","answer":"TERRY","a":"03","b":"10"},{"clue":"Gulf V.I.P.","answer":"EMIR","a":"03","b":"10"},{"clue":"Hopping John ingredient","answer":"RICE","a":"03","b":"10"},{"clue":"Anthologies","answer":"ANAS","a":"03","b":"10"},{"clue":"More suitable for a job","answer":"ABLER","a":"03","b":"10"},{"clue":"Mezzo Berganza","answer":"TERESA","a":"03","b":"10"},{"clue":"Stand buys","answer":"ADES","a":"03","b":"10"},{"clue":"Common computer icon","answer":"MAILBOX","a":"03","b":"10"},{"clue":"Airs","answer":"LILTS","a":"03","b":"10"},{"clue":"Correct","answer":"REDPENCIL","a":"03","b":"10"},{"clue":"Fruity dessert","answer":"PANDOWDY","a":"03","b":"10"},{"clue":"Sincere","answer":"FORREAL","a":"03","b":"10"},{"clue":"Front-of-car accessory","answer":"FOGLAMP","a":"03","b":"10"},{"clue":"Not so bright","answer":"OBTUSER","a":"03","b":"10"},{"clue":"Goes for","answer":"ELECTS","a":"03","b":"10"},{"clue":"Sticks","answer":"COHERES","a":"03","b":"10"},{"clue":"Dollface","answer":"TOOTSIE","a":"03","b":"10"},{"clue":"Ductless organs","answer":"SPLEENS","a":"03","b":"10"},{"clue":"Pass","answer":"GOBY","a":"03","b":"10"},{"clue":"Big cuts","answer":"GASHES","a":"03","b":"10"},{"clue":"Saucy sort","answer":"SNIP","a":"03","b":"10"},{"clue":"Lunchbox item, for short","answer":"PBANDJ","a":"03","b":"10"},{"clue":"March","answer":"TROOP","a":"03","b":"10"},{"clue":"Bond, e.g.: Abbr.","answer":"AGT","a":"03","b":"10"},{"clue":"They must be satisfied","answer":"DEBTS","a":"03","b":"10"},{"clue":"Detailed, briefly","answer":"THORO","a":"03","b":"10"},{"clue":"Christmas, e.g.: Abbr.","answer":"HOL","a":"03","b":"10"},{"clue":"Disparage","answer":"SLUR","a":"03","b":"10"},{"clue":"Singular, to Caesar","answer":"RARA","a":"03","b":"10"},{"clue":"Numbers holder","answer":"TORAH","a":"03","b":"10"},{"clue":"___ call","answer":"TOLL","a":"03","b":"10"},{"clue":"Give (out)","answer":"METE","a":"03","b":"10"},{"clue":"Turn","answer":"MOVE","a":"03","b":"10"},{"clue":"Goes nuts","answer":"HASACOW","a":"03","b":"10"},{"clue":"Field call","answer":"CAW","a":"03","b":"10"},{"clue":"\"The same,\" in condition","answer":"NOWORSE","a":"03","b":"10"},{"clue":"Sports page statistic","answer":"WIN","a":"03","b":"10"},{"clue":"___ City of story and film","answer":"EMERALD","a":"03","b":"10"},{"clue":"Kind of window","answer":"DRIVEIN","a":"03","b":"10"},{"clue":"Very spread out","answer":"SPRAWLY","a":"03","b":"10"},{"clue":"Neighbors, figuratively","answer":"JONESES","a":"03","b":"10"},{"clue":"Directory","answer":"LIST","a":"03","b":"3"},{"clue":"Nicholson role in \"Easy Rider\"","answer":"LAWYER","a":"03","b":"3"},{"clue":"Bury","answer":"INHUME","a":"03","b":"3"},{"clue":"Nicholson role in \"The Last Detail\"","answer":"SAILOR","a":"03","b":"3"},{"clue":"Child's dose, maybe: Abbr.","answer":"TSP","a":"03","b":"3"},{"clue":"Opposite of kitsch","answer":"TASTE","a":"03","b":"3"},{"clue":"It may be magnetic","answer":"TAPE","a":"03","b":"3"},{"clue":"Take ___ (travel)","answer":"ATRIP","a":"03","b":"3"},{"clue":"Bake, in a way","answer":"SHIRR","a":"03","b":"3"},{"clue":"\"Mazel ___!\"","answer":"TOV","a":"03","b":"3"},{"clue":"Go by","answer":"ELAPSE","a":"03","b":"3"},{"clue":"Exhaustive","answer":"ATOZ","a":"03","b":"3"},{"clue":"Add to or subtract from","answer":"AMEND","a":"03","b":"3"},{"clue":"Was indecisive","answer":"TEETERED","a":"03","b":"3"},{"clue":"Suffix with access","answer":"ORY","a":"03","b":"3"},{"clue":"Zuyder ___","answer":"ZEE","a":"03","b":"3"},{"clue":"Comic Gasteyer and others","answer":"ANAS","a":"03","b":"3"},{"clue":"Playwright Fugard","answer":"ATHOL","a":"03","b":"3"},{"clue":"Nothing but","answer":"MERE","a":"03","b":"3"},{"clue":"Senate V.I.P.","answer":"WHIP","a":"03","b":"3"},{"clue":"Nicholson role in \"Chinatown\"","answer":"PRIVATEEYE","a":"03","b":"3"},{"clue":"See 45-Across","answer":"TAIS","a":"03","b":"3"},{"clue":"Gertrude's 1951 Broadway co-star","answer":"YUL","a":"03","b":"3"},{"clue":"Dayan colleague","answer":"MEIR","a":"03","b":"3"},{"clue":"\"I feel the same way\"","answer":"METOO","a":"03","b":"3"},{"clue":"___ cuffs","answer":"PANT","a":"03","b":"3"},{"clue":"Play too broadly","answer":"EMOTE","a":"03","b":"3"},{"clue":"Undertakings","answer":"TASKS","a":"03","b":"3"},{"clue":"Nicholson role in \"Mars Attacks!\"","answer":"PRESIDENT","a":"03","b":"3"},{"clue":"Viscounts' superiors","answer":"EARLS","a":"03","b":"3"},{"clue":"Musical with the song \"Be Italian\"","answer":"NINE","a":"03","b":"3"},{"clue":"Day-care charges","answer":"TOTS","a":"03","b":"3"},{"clue":"Change from AA to AAA, e.g.","answer":"RERATE","a":"03","b":"3"},{"clue":"Gnome","answer":"ELF","a":"03","b":"3"},{"clue":"Two-time Dem. nominee","answer":"AES","a":"03","b":"3"},{"clue":"Where Sugarloaf Mountain is","answer":"RIO","a":"03","b":"3"},{"clue":"You, for one","answer":"SOLVER","a":"03","b":"3"},{"clue":"Carrier to 32-Across","answer":"VARIG","a":"03","b":"3"},{"clue":"\"Do Ya\" grp.","answer":"ELO","a":"03","b":"3"},{"clue":"___-up (confined)","answer":"PENT","a":"03","b":"3"},{"clue":"Start of a long story?","answer":"PARTI","a":"03","b":"3"},{"clue":"Apt title for this puzzle","answer":"JACKOFALLTRADES","a":"03","b":"3"},{"clue":"Olympic event since 1972","answer":"JUDO","a":"03","b":"3"},{"clue":"Cultural beginning?","answer":"AGRI","a":"03","b":"3"},{"clue":"Relax","answer":"CHILLOUT","a":"03","b":"3"},{"clue":"Pharmacist's abbr.","answer":"TID","a":"03","b":"3"},{"clue":"Teammate of Snider and Hodges","answer":"REESE","a":"03","b":"3"},{"clue":"Words with grimaces","answer":"UGHS","a":"03","b":"3"},{"clue":"More favorable","answer":"ROSIER","a":"03","b":"3"},{"clue":"Soft & ___ (Gillette product)","answer":"DRI","a":"03","b":"3"},{"clue":"With 19-Down, rum drinks","answer":"MAI","a":"03","b":"3"},{"clue":"Street performer","answer":"MIME","a":"03","b":"3"},{"clue":"Moroccan port","answer":"AGADIR","a":"03","b":"3"},{"clue":"Unfasten","answer":"DETACH","a":"03","b":"3"},{"clue":"Nicholson role in \"Broadcast News\"","answer":"ANCHOR","a":"03","b":"3"},{"clue":"Where a dealer deals","answer":"CASINO","a":"03","b":"3"},{"clue":"Nicholson role in \"Prizzi's Honor\"","answer":"HITMAN","a":"03","b":"3"},{"clue":"Nicholson role in \"Five Easy Pieces\"","answer":"OILRIGGER","a":"03","b":"3"},{"clue":"49-Down tools","answer":"RAKES","a":"03","b":"3"},{"clue":"Join","answer":"ENTER","a":"03","b":"3"},{"clue":"News exec Arledge","answer":"ROONE","a":"03","b":"3"},{"clue":"Mideast hot spot","answer":"SINAI","a":"03","b":"3"},{"clue":"Priest from the East","answer":"LAMA","a":"03","b":"3"},{"clue":"Melody part","answer":"NOTE","a":"03","b":"3"},{"clue":"Gallows","answer":"TREE","a":"03","b":"3"},{"clue":"Iowa hrs.","answer":"CST","a":"03","b":"3"},{"clue":"Nicholson role in \"Wolf\"","answer":"BOOKEDITOR","a":"03","b":"3"},{"clue":"Dude","answer":"BRO","a":"03","b":"3"},{"clue":"Alley ___","answer":"OOP","a":"03","b":"3"},{"clue":"Author Levin","answer":"IRA","a":"03","b":"3"},{"clue":"Fancy","answer":"WHIM","a":"03","b":"3"},{"clue":"Raconteur's asset","answer":"WIT","a":"03","b":"3"},{"clue":"Libertine","answer":"ROUE","a":"03","b":"3"},{"clue":"\"Goodnight ___\"","answer":"IRENE","a":"03","b":"3"},{"clue":"Hebrides island","answer":"IONA","a":"03","b":"3"},{"clue":"Picks","answer":"OPTS","a":"03","b":"3"},{"clue":"Street show","answer":"RAREE","a":"03","b":"3"},{"clue":"Disney film with a video-game contest","answer":"TRON","a":"03","b":"3"},{"clue":"Slacken","answer":"ABATE","a":"03","b":"12"},{"clue":"Mars' counterpart","answer":"ARES","a":"03","b":"12"},{"clue":"Island near Java","answer":"BALI","a":"03","b":"12"},{"clue":"Yemeni port","answer":"ADEN","a":"03","b":"12"},{"clue":"What a comb undoes","answer":"TANGLE","a":"03","b":"12"},{"clue":"Pencil features","answer":"ERASERS","a":"03","b":"12"},{"clue":"Disparaging remark","answer":"SLUR","a":"03","b":"12"},{"clue":"Witness-box","answer":"STAND","a":"03","b":"12"},{"clue":"Men's jacket size","answer":"LONG","a":"03","b":"12"},{"clue":"Martian's craft, for short","answer":"UFO","a":"03","b":"12"},{"clue":"Takes to the station house","answer":"RUNSIN","a":"03","b":"12"},{"clue":"Dog ___ (G.I. identifiers)","answer":"TAGS","a":"03","b":"12"},{"clue":"Roofing base","answer":"TARPAPER","a":"03","b":"12"},{"clue":"Help in piracy, e.g.","answer":"ABET","a":"03","b":"12"},{"clue":"Heredity carrier","answer":"GENE","a":"03","b":"12"},{"clue":"Piggy-bank aperture","answer":"SLOT","a":"03","b":"12"},{"clue":"Speeder's bane","answer":"RADAR","a":"03","b":"12"},{"clue":"Sukiyaki ingredient","answer":"TOFU","a":"03","b":"12"},{"clue":"Cain's victim","answer":"ABEL","a":"03","b":"12"},{"clue":"Actress Verdugo","answer":"ELENA","a":"03","b":"12"},{"clue":"Shortly","answer":"ANON","a":"03","b":"12"},{"clue":"Divorce mecca","answer":"RENO","a":"03","b":"12"},{"clue":"Like doggerel, often","answer":"SINGSONG","a":"03","b":"12"},{"clue":"Desert stops","answer":"OASES","a":"03","b":"12"},{"clue":"Chamber group, maybe","answer":"SEPTET","a":"03","b":"12"},{"clue":"Metric work units","answer":"ERGS","a":"03","b":"12"},{"clue":"Make the first moves, in dancing","answer":"LEAD","a":"03","b":"12"},{"clue":"Former Italian money","answer":"LIRA","a":"03","b":"12"},{"clue":"Stocking material","answer":"LISLE","a":"03","b":"12"},{"clue":"Dogie catchers","answer":"ROPERS","a":"03","b":"12"},{"clue":"Angry, with \"up\"","answer":"RILED","a":"03","b":"12"},{"clue":"Latin eyes","answer":"OCULI","a":"03","b":"12"},{"clue":"Aircraft course marker","answer":"PYLON","a":"03","b":"12"},{"clue":"Game with an onomatopoeic name","answer":"PINGPONG","a":"03","b":"12"},{"clue":"Fork tine","answer":"PRONG","a":"03","b":"12"},{"clue":"Tatum of Tinseltown","answer":"ONEAL","a":"03","b":"12"},{"clue":"Chivalrous","answer":"NOBLE","a":"03","b":"12"},{"clue":"Add on, as to a plant","answer":"GRAFT","a":"03","b":"12"},{"clue":"Frigid","answer":"ICY","a":"03","b":"12"},{"clue":"Company with a once-famous catalog","answer":"SEARS","a":"03","b":"12"},{"clue":"Making a hole in one","answer":"ACING","a":"03","b":"12"},{"clue":"Mister in Mexico","answer":"SENOR","a":"03","b":"12"},{"clue":"Ripsnorter","answer":"LULU","a":"03","b":"12"}]